{"stats":{"minecraft:picked_up":{"immersive_weathering:permafrost":2,"biomesoplenty:maple_log":1},"minecraft:mined":{"immersive_weathering:grassy_permafrost":2},"minecraft:dropped":{"biomesoplenty:wildflower":1,"biomesoplenty:maple_log":1},"minecraft:used":{"biomesoplenty:maple_log":2,"minecraft:flint_and_steel":75},"minecraft:custom":{"minecraft:jump":58,"minecraft:time_since_rest":26355,"minecraft:crouch_one_cm":401,"minecraft:leave_game":1,"minecraft:sprint_one_cm":5488,"minecraft:play_time":26355,"minecraft:time_since_death":26355,"minecraft:walk_one_cm":8584,"minecraft:sneak_time":260,"minecraft:total_world_time":26355,"minecraft:drop":2,"minecraft:fall_one_cm":209,"minecraft:fly_one_cm":40402}},"DataVersion":3465}